<?xml version='1.0' encoding='UTF-8'?>
<hudson.plugins.disk__usage.ProjectDiskUsage plugin="disk-usage@0.25">
  <diskUsageWithoutBuilds>287866592</diskUsageWithoutBuilds>
  <slaveWorkspacesUsage class="concurrent-hash-map">
    <entry>
      <string></string>
      <concurrent-hash-map>
        <entry>
          <string>/home/jenkins/jobs/Elexis-3.0-Base-ngiger/workspace</string>
          <long>42052254</long>
        </entry>
      </concurrent-hash-map>
    </entry>
  </slaveWorkspacesUsage>
  <buildDiskUsage>
    <hudson.plugins.disk__usage.DiskUsageBuildInformation>
      <id>2015-01-09_10-37-47</id>
      <timestamp>1420796267000</timestamp>
      <number>51</number>
      <size>94740664</size>
    </hudson.plugins.disk__usage.DiskUsageBuildInformation>
    <hudson.plugins.disk__usage.DiskUsageBuildInformation>
      <id>2014-12-23_08-57-37</id>
      <timestamp>1419321457000</timestamp>
      <number>49</number>
      <size>95696901</size>
    </hudson.plugins.disk__usage.DiskUsageBuildInformation>
    <hudson.plugins.disk__usage.DiskUsageBuildInformation>
      <id>2015-01-16_14-50-10</id>
      <timestamp>1421416210000</timestamp>
      <number>52</number>
      <size>94769311</size>
    </hudson.plugins.disk__usage.DiskUsageBuildInformation>
    <hudson.plugins.disk__usage.DiskUsageBuildInformation>
      <id>2014-12-22_08-45-10</id>
      <timestamp>1419234310000</timestamp>
      <number>47</number>
      <size>94528746</size>
    </hudson.plugins.disk__usage.DiskUsageBuildInformation>
    <hudson.plugins.disk__usage.DiskUsageBuildInformation>
      <id>2015-01-08_22-37-09</id>
      <timestamp>1420753029000</timestamp>
      <number>50</number>
      <size>94739442</size>
    </hudson.plugins.disk__usage.DiskUsageBuildInformation>
    <hudson.plugins.disk__usage.DiskUsageBuildInformation>
      <id>2014-11-21_00-00-09</id>
      <timestamp>1416524409000</timestamp>
      <number>45</number>
      <size>93315167</size>
    </hudson.plugins.disk__usage.DiskUsageBuildInformation>
    <hudson.plugins.disk__usage.DiskUsageBuildInformation>
      <id>2014-12-18_13-35-07</id>
      <timestamp>1418906107000</timestamp>
      <number>46</number>
      <size>94485371</size>
    </hudson.plugins.disk__usage.DiskUsageBuildInformation>
    <hudson.plugins.disk__usage.DiskUsageBuildInformation>
      <id>2014-12-22_22-08-16</id>
      <timestamp>1419282496000</timestamp>
      <number>48</number>
      <size>94511285</size>
    </hudson.plugins.disk__usage.DiskUsageBuildInformation>
    <hudson.plugins.disk__usage.DiskUsageBuildInformation>
      <id>2014-11-20_19-15-07</id>
      <timestamp>1416507307000</timestamp>
      <number>44</number>
      <size>93309055</size>
    </hudson.plugins.disk__usage.DiskUsageBuildInformation>
    <hudson.plugins.disk__usage.DiskUsageBuildInformation>
      <id>2014-11-20_11-40-07</id>
      <timestamp>1416480007000</timestamp>
      <number>43</number>
      <size>93316343</size>
    </hudson.plugins.disk__usage.DiskUsageBuildInformation>
  </buildDiskUsage>
</hudson.plugins.disk__usage.ProjectDiskUsage>